instacerty/__init__.py
instacerty/instacerty.py
instacerty/utils.py
instacerty/id_card_generator/__init__.py
instacerty/id_card_generator/_common.py
instacerty/id_card_generator/employee_card.py
instacerty/id_card_generator/enums.py
instacerty/id_card_generator/generator.py
instacerty/id_card_generator/static/fonts/Roboto-Bold.ttf
instacerty/id_card_generator/static/fonts/Roboto-Light.ttf
instacerty/id_card_generator/static/fonts/Roboto-Medium.ttf
instacerty/id_card_generator/static/fonts/Roboto-Regular.ttf
instacerty/id_card_generator/static/templates/Profile_Picture.png
instacerty/id_card_generator/static/templates/back_company_logo.png
instacerty/id_card_generator/static/templates/back_side.png
instacerty/id_card_generator/static/templates/company_logo.png
instacerty/id_card_generator/static/templates/front_side_circle.png
instacerty/id_card_generator/static/templates/front_side_rounded.png
instacerty/id_card_generator/static/templates/front_side_square.png
instacerty/static/images/badge.png
instacerty/static/images/bg.jpg
instacerty/static/images/signature.png
instacerty-2.0.0.dist-info/LICENSE
instacerty-2.0.0.dist-info/METADATA
instacerty-2.0.0.dist-info/WHEEL
instacerty-2.0.0.dist-info/top_level.txt
instacerty-2.0.0.dist-info/RECORD
